pypidfile
