Metadata-Version: 2.1
Name: pypidfile
Version: 0.0.2
Summary: Pid file management
Home-page: https://github.com/pietrogiuffrida/pypidfile/
Author: Pietro Giuffrida
Author-email: pietro.giuffri@gmail.com
License: MIT
Platform: UNKNOWN
Classifier: Programming Language :: Python :: 3
Classifier: License :: OSI Approved :: MIT License
Classifier: Operating System :: OS Independent
